<?xml version = '1.0' encoding = 'UTF-8'?>
<TableProxyOraclev12c class="oracle.dbtools.crest.model.design.storage.oracle.v12c.TableProxyOraclev12c" name="ARTICULOS" directorySegmentName="seg_0" id="B0484B7F-27FF-461A-ACC1-F7E57E623929">
<createdBy>1gdaw06</createdBy>
<createdTime>2019-11-21 11:48:35 UTC</createdTime>
<ownerDesignName>04_MER</ownerDesignName>
<logging>YES</logging>
<partitionedRowMovement>DISABLE</partitionedRowMovement>
<temporaryChanged>false</temporaryChanged>
<accessDriverType>oracle_loader</accessDriverType>
<rejectLimit></rejectLimit>
<columnProxies itemClass="oracle.dbtools.crest.model.design.storage.oracle.v12c.ColumnProxyOraclev12c">
<ColumnProxy name="EXISTENCIAS" id="00C6CB09-8A53-4E8B-B8C9-FDFAFAE0B69C">
<createdBy>1gdaw06</createdBy>
<createdTime>2019-11-21 11:48:35 UTC</createdTime>
<ownerDesignName>04_MER</ownerDesignName>
</ColumnProxy>
<ColumnProxy name="CATEGORIA" id="4E18808D-967E-6F10-05F5-221F993A0BA5">
<createdBy>1gdaw06</createdBy>
<createdTime>2019-11-21 11:48:35 UTC</createdTime>
<ownerDesignName>04_MER</ownerDesignName>
</ColumnProxy>
<ColumnProxy name="COD_FABRICANTE" id="69D58D56-0EE2-9FC3-B160-DDC68666FBB1">
<createdBy>1gdaw06</createdBy>
<createdTime>2019-11-21 11:48:35 UTC</createdTime>
<ownerDesignName>04_MER</ownerDesignName>
</ColumnProxy>
<ColumnProxy name="ARTICULO" id="8366638A-D555-16AB-E44D-76E57E1C5019">
<createdBy>1gdaw06</createdBy>
<createdTime>2019-11-21 11:48:35 UTC</createdTime>
<ownerDesignName>04_MER</ownerDesignName>
</ColumnProxy>
<ColumnProxy name="PRECIO_VENTA" id="9198B665-02D0-C5C9-1AF7-26821FAC780C">
<createdBy>1gdaw06</createdBy>
<createdTime>2019-11-21 11:48:35 UTC</createdTime>
<ownerDesignName>04_MER</ownerDesignName>
</ColumnProxy>
<ColumnProxy name="PRECIO_COSTO" id="ACB95FB1-F9D2-7FBD-32D2-6A65B74BC5BC">
<createdBy>1gdaw06</createdBy>
<createdTime>2019-11-21 11:48:35 UTC</createdTime>
<ownerDesignName>04_MER</ownerDesignName>
</ColumnProxy>
<ColumnProxy name="PESO" id="BC439BB9-97BF-D766-8BF2-1AD66430375A">
<createdBy>1gdaw06</createdBy>
<createdTime>2019-11-21 11:48:35 UTC</createdTime>
<ownerDesignName>04_MER</ownerDesignName>
</ColumnProxy>
</columnProxies>
<foreignKeys>
<ForeignKey class="oracle.dbtools.crest.model.design.storage.oracle.v10g.FKProxyOraclev10g" name="ART_COD_FK" id="D19C71F1-379E-213F-6C35-741956857CCB">
<createdBy>1gdaw06</createdBy>
<createdTime>2019-11-21 11:48:35 UTC</createdTime>
<ownerDesignName>04_MER</ownerDesignName>
</ForeignKey>
</foreignKeys>
<primaryKeys>
<PrimaryKey class="oracle.dbtools.crest.model.design.storage.oracle.v10g.PKProxyOraclev10g" name="ART_PK" id="770E9881-E402-9FE5-0B08-6212D2528AD3">
<createdBy>1gdaw06</createdBy>
<createdTime>2019-11-21 11:48:35 UTC</createdTime>
<ownerDesignName>04_MER</ownerDesignName>
<indexSort>SORTED</indexSort>
</PrimaryKey>
</primaryKeys>
<tableCheckConstraints itemClass="oracle.dbtools.crest.model.design.storage.oracle.TableCheckConstraintOracle">
<TableCheckConstraint name="ART_PREV_CK" id="C788D9CD-ECA0-98DB-112A-73D700B9D30F">
<createdBy>1gdaw06</createdBy>
<createdTime>2019-11-21 11:48:35 UTC</createdTime>
<ownerDesignName>04_MER</ownerDesignName>
<nameChanged>true</nameChanged>
</TableCheckConstraint>
<TableCheckConstraint name="ART_PREC_CK" id="D1D4373D-F48D-FD27-67F8-A60B511ED1C7">
<createdBy>1gdaw06</createdBy>
<createdTime>2019-11-21 11:48:35 UTC</createdTime>
<ownerDesignName>04_MER</ownerDesignName>
<nameChanged>true</nameChanged>
</TableCheckConstraint>
<TableCheckConstraint name="ART_PES_CK" id="EA6BF2CF-1DBE-E67E-BF95-1C6BF98CBC65">
<createdBy>1gdaw06</createdBy>
<createdTime>2019-11-21 11:48:35 UTC</createdTime>
<ownerDesignName>04_MER</ownerDesignName>
<nameChanged>true</nameChanged>
</TableCheckConstraint>
<TableCheckConstraint name="ART_CAT_CK" id="EDFE281C-08B3-AC4C-FA52-2DB2E0066596">
<createdBy>1gdaw06</createdBy>
<createdTime>2019-11-21 11:48:35 UTC</createdTime>
<ownerDesignName>04_MER</ownerDesignName>
<nameChanged>true</nameChanged>
</TableCheckConstraint>
</tableCheckConstraints>
</TableProxyOraclev12c>